{"otherData": {},"traceEvents":[
{
"cat":"function",
"dur":15,
"name":"int __cdecl ScrewSandbox::Sandbox::PullEvents(void)",
"ph":"X",
"pid":50448,
"tid":10433558269746414945,
"ts":20794757
}
,
{
"cat":"function",
"dur":15,
"name":"int __cdecl ScrewSandbox::Sandbox::Update(void)",
"ph":"X",
"pid":50448,
"tid":10433558269746414945,
"ts":20794773
}
,
{
"cat":"function",
"dur":16,
"name":"int __cdecl ScrewSandbox::Sandbox::Output(void)",
"ph":"X",
"pid":50448,
"tid":10433558269746414945,
"ts":20794788
}
,
{
"cat":"function",
"dur":63,
"name":"void __cdecl ScrewSandbox::Sandbox::RunLoop(void)",
"ph":"X",
"pid":50448,
"tid":10433558269746414945,
"ts":20794741
}
,
{
"cat":"function",
"dur":16,
"name":"int __cdecl ScrewSandbox::Sandbox::PullEvents(void)",
"ph":"X",
"pid":50448,
"tid":10433558269746414945,
"ts":20794819
}
,
{
"cat":"function",
"dur":15,
"name":"int __cdecl ScrewSandbox::Sandbox::Update(void)",
"ph":"X",
"pid":50448,
"tid":10433558269746414945,
"ts":20794835
}
,
{
"cat":"function",
"dur":15,
"name":"int __cdecl ScrewSandbox::Sandbox::Output(void)",
"ph":"X",
"pid":50448,
"tid":10433558269746414945,
"ts":20794851
}
,
{
"cat":"function",
"dur":61,
"name":"void __cdecl ScrewSandbox::Sandbox::RunLoop(void)",
"ph":"X",
"pid":50448,
"tid":10433558269746414945,
"ts":20794805
}
,
{
"cat":"function",
"dur":15,
"name":"int __cdecl ScrewSandbox::Sandbox::PullEvents(void)",
"ph":"X",
"pid":50448,
"tid":10433558269746414945,
"ts":20794882
}
,
{
"cat":"function",
"dur":15,
"name":"int __cdecl ScrewSandbox::Sandbox::Update(void)",
"ph":"X",
"pid":50448,
"tid":10433558269746414945,
"ts":20794898
}
,
{
"cat":"function",
"dur":15,
"name":"int __cdecl ScrewSandbox::Sandbox::Output(void)",
"ph":"X",
"pid":50448,
"tid":10433558269746414945,
"ts":20794914
}
,
{
"cat":"function",
"dur":63,
"name":"void __cdecl ScrewSandbox::Sandbox::RunLoop(void)",
"ph":"X",
"pid":50448,
"tid":10433558269746414945,
"ts":20794866
}
,
{
"cat":"function",
"dur":15,
"name":"int __cdecl ScrewSandbox::Sandbox::PullEvents(void)",
"ph":"X",
"pid":50448,
"tid":10433558269746414945,
"ts":20794945
}
,
{
"cat":"function",
"dur":16,
"name":"int __cdecl ScrewSandbox::Sandbox::Update(void)",
"ph":"X",
"pid":50448,
"tid":10433558269746414945,
"ts":20794960
}
,
{
"cat":"function",
"dur":15,
"name":"int __cdecl ScrewSandbox::Sandbox::Output(void)",
"ph":"X",
"pid":50448,
"tid":10433558269746414945,
"ts":20794976
}
,
{
"cat":"function",
"dur":62,
"name":"void __cdecl ScrewSandbox::Sandbox::RunLoop(void)",
"ph":"X",
"pid":50448,
"tid":10433558269746414945,
"ts":20794929
}
,
{
"cat":"function",
"dur":16,
"name":"int __cdecl ScrewSandbox::Sandbox::PullEvents(void)",
"ph":"X",
"pid":50448,
"tid":10433558269746414945,
"ts":20795007
}
,
{
"cat":"function",
"dur":15,
"name":"int __cdecl ScrewSandbox::Sandbox::Update(void)",
"ph":"X",
"pid":50448,
"tid":10433558269746414945,
"ts":20795023
}
,
{
"cat":"function",
"dur":15,
"name":"int __cdecl ScrewSandbox::Sandbox::Output(void)",
"ph":"X",
"pid":50448,
"tid":10433558269746414945,
"ts":20795039
}
,
{
"cat":"function",
"dur":64,
"name":"void __cdecl ScrewSandbox::Sandbox::RunLoop(void)",
"ph":"X",
"pid":50448,
"tid":10433558269746414945,
"ts":20794991
}
,
{
"cat":"function",
"dur":15,
"name":"int __cdecl ScrewSandbox::Sandbox::PullEvents(void)",
"ph":"X",
"pid":50448,
"tid":10433558269746414945,
"ts":20795070
}
,
{
"cat":"function",
"dur":15,
"name":"int __cdecl ScrewSandbox::Sandbox::Update(void)",
"ph":"X",
"pid":50448,
"tid":10433558269746414945,
"ts":20795085
}
,
{
"cat":"function",
"dur":16,
"name":"int __cdecl ScrewSandbox::Sandbox::Output(void)",
"ph":"X",
"pid":50448,
"tid":10433558269746414945,
"ts":20795101
}
,
{
"cat":"function",
"dur":62,
"name":"void __cdecl ScrewSandbox::Sandbox::RunLoop(void)",
"ph":"X",
"pid":50448,
"tid":10433558269746414945,
"ts":20795055
}
,
{
"cat":"function",
"dur":15,
"name":"int __cdecl ScrewSandbox::Sandbox::PullEvents(void)",
"ph":"X",
"pid":50448,
"tid":10433558269746414945,
"ts":20795133
}
,
{
"cat":"function",
"dur":15,
"name":"int __cdecl ScrewSandbox::Sandbox::Update(void)",
"ph":"X",
"pid":50448,
"tid":10433558269746414945,
"ts":20795148
}
,
{
"cat":"function",
"dur":15,
"name":"int __cdecl ScrewSandbox::Sandbox::Output(void)",
"ph":"X",
"pid":50448,
"tid":10433558269746414945,
"ts":20795163
}
,
{
"cat":"function",
"dur":61,
"name":"void __cdecl ScrewSandbox::Sandbox::RunLoop(void)",
"ph":"X",
"pid":50448,
"tid":10433558269746414945,
"ts":20795117
}
,
{
"cat":"function",
"dur":16,
"name":"int __cdecl ScrewSandbox::Sandbox::PullEvents(void)",
"ph":"X",
"pid":50448,
"tid":10433558269746414945,
"ts":20795194
}
,
{
"cat":"function",
"dur":16,
"name":"int __cdecl ScrewSandbox::Sandbox::Update(void)",
"ph":"X",
"pid":50448,
"tid":10433558269746414945,
"ts":20795210
}
,
{
"cat":"function",
"dur":15,
"name":"int __cdecl ScrewSandbox::Sandbox::Output(void)",
"ph":"X",
"pid":50448,
"tid":10433558269746414945,
"ts":20795226
}
,
{
"cat":"function",
"dur":64,
"name":"void __cdecl ScrewSandbox::Sandbox::RunLoop(void)",
"ph":"X",
"pid":50448,
"tid":10433558269746414945,
"ts":20795178
}
,
{
"cat":"function",
"dur":16,
"name":"int __cdecl ScrewSandbox::Sandbox::PullEvents(void)",
"ph":"X",
"pid":50448,
"tid":10433558269746414945,
"ts":20795257
}
,
{
"cat":"function",
"dur":15,
"name":"int __cdecl ScrewSandbox::Sandbox::Update(void)",
"ph":"X",
"pid":50448,
"tid":10433558269746414945,
"ts":20795273
}
,
{
"cat":"function",
"dur":16,
"name":"int __cdecl ScrewSandbox::Sandbox::Output(void)",
"ph":"X",
"pid":50448,
"tid":10433558269746414945,
"ts":20795289
}
,
{
"cat":"function",
"dur":63,
"name":"void __cdecl ScrewSandbox::Sandbox::RunLoop(void)",
"ph":"X",
"pid":50448,
"tid":10433558269746414945,
"ts":20795242
}
,
{
"cat":"function",
"dur":16,
"name":"int __cdecl ScrewSandbox::Sandbox::PullEvents(void)",
"ph":"X",
"pid":50448,
"tid":10433558269746414945,
"ts":20795320
}
,
{
"cat":"function",
"dur":15,
"name":"int __cdecl ScrewSandbox::Sandbox::Update(void)",
"ph":"X",
"pid":50448,
"tid":10433558269746414945,
"ts":20795336
}
,
{
"cat":"function",
"dur":16,
"name":"int __cdecl ScrewSandbox::Sandbox::Output(void)",
"ph":"X",
"pid":50448,
"tid":10433558269746414945,
"ts":20795351
}
,
{
"cat":"function",
"dur":62,
"name":"void __cdecl ScrewSandbox::Sandbox::RunLoop(void)",
"ph":"X",
"pid":50448,
"tid":10433558269746414945,
"ts":20795305
}
,
{
"cat":"function",
"dur":15,
"name":"int __cdecl ScrewSandbox::Sandbox::PullEvents(void)",
"ph":"X",
"pid":50448,
"tid":10433558269746414945,
"ts":20795383
}
,
{
"cat":"function",
"dur":15,
"name":"int __cdecl ScrewSandbox::Sandbox::Update(void)",
"ph":"X",
"pid":50448,
"tid":10433558269746414945,
"ts":20795398
}
,
{
"cat":"function",
"dur":16,
"name":"int __cdecl ScrewSandbox::Sandbox::Output(void)",
"ph":"X",
"pid":50448,
"tid":10433558269746414945,
"ts":20795413
}
,
{
"cat":"function",
"dur":62,
"name":"void __cdecl ScrewSandbox::Sandbox::RunLoop(void)",
"ph":"X",
"pid":50448,
"tid":10433558269746414945,
"ts":20795367
}
,
{
"cat":"function",
"dur":15,
"name":"int __cdecl ScrewSandbox::Sandbox::PullEvents(void)",
"ph":"X",
"pid":50448,
"tid":10433558269746414945,
"ts":20795444
}
,
{
"cat":"function",
"dur":15,
"name":"int __cdecl ScrewSandbox::Sandbox::Update(void)",
"ph":"X",
"pid":50448,
"tid":10433558269746414945,
"ts":20795460
}
,
{
"cat":"function",
"dur":15,
"name":"int __cdecl ScrewSandbox::Sandbox::Output(void)",
"ph":"X",
"pid":50448,
"tid":10433558269746414945,
"ts":20795476
}
,
{
"cat":"function",
"dur":62,
"name":"void __cdecl ScrewSandbox::Sandbox::RunLoop(void)",
"ph":"X",
"pid":50448,
"tid":10433558269746414945,
"ts":20795429
}
,
{
"cat":"function",
"dur":15,
"name":"int __cdecl ScrewSandbox::Sandbox::PullEvents(void)",
"ph":"X",
"pid":50448,
"tid":10433558269746414945,
"ts":20795507
}
,
{
"cat":"function",
"dur":15,
"name":"int __cdecl ScrewSandbox::Sandbox::Update(void)",
"ph":"X",
"pid":50448,
"tid":10433558269746414945,
"ts":20795523
}
,
{
"cat":"function",
"dur":15,
"name":"int __cdecl ScrewSandbox::Sandbox::Output(void)",
"ph":"X",
"pid":50448,
"tid":10433558269746414945,
"ts":20795539
}
,
{
"cat":"function",
"dur":63,
"name":"void __cdecl ScrewSandbox::Sandbox::RunLoop(void)",
"ph":"X",
"pid":50448,
"tid":10433558269746414945,
"ts":20795491
}
,
{
"cat":"function",
"dur":15,
"name":"int __cdecl ScrewSandbox::Sandbox::PullEvents(void)",
"ph":"X",
"pid":50448,
"tid":10433558269746414945,
"ts":20795569
}
,
{
"cat":"function",
"dur":15,
"name":"int __cdecl ScrewSandbox::Sandbox::Update(void)",
"ph":"X",
"pid":50448,
"tid":10433558269746414945,
"ts":20795584
}
,
{
"cat":"function",
"dur":15,
"name":"int __cdecl ScrewSandbox::Sandbox::Output(void)",
"ph":"X",
"pid":50448,
"tid":10433558269746414945,
"ts":20795600
}
,
{
"cat":"function",
"dur":61,
"name":"void __cdecl ScrewSandbox::Sandbox::RunLoop(void)",
"ph":"X",
"pid":50448,
"tid":10433558269746414945,
"ts":20795554
}
,
{
"cat":"function",
"dur":16,
"name":"int __cdecl ScrewSandbox::Sandbox::PullEvents(void)",
"ph":"X",
"pid":50448,
"tid":10433558269746414945,
"ts":20795631
}
,
{
"cat":"function",
"dur":16,
"name":"int __cdecl ScrewSandbox::Sandbox::Update(void)",
"ph":"X",
"pid":50448,
"tid":10433558269746414945,
"ts":20795647
}
,
{
"cat":"function",
"dur":15,
"name":"int __cdecl ScrewSandbox::Sandbox::Output(void)",
"ph":"X",
"pid":50448,
"tid":10433558269746414945,
"ts":20795663
}
,
{
"cat":"function",
"dur":63,
"name":"void __cdecl ScrewSandbox::Sandbox::RunLoop(void)",
"ph":"X",
"pid":50448,
"tid":10433558269746414945,
"ts":20795615
}
,
{
"cat":"function",
"dur":15,
"name":"int __cdecl ScrewSandbox::Sandbox::PullEvents(void)",
"ph":"X",
"pid":50448,
"tid":10433558269746414945,
"ts":20795693
}
,
{
"cat":"function",
"dur":15,
"name":"int __cdecl ScrewSandbox::Sandbox::Update(void)",
"ph":"X",
"pid":50448,
"tid":10433558269746414945,
"ts":20795708
}
,
{
"cat":"function",
"dur":16,
"name":"int __cdecl ScrewSandbox::Sandbox::Output(void)",
"ph":"X",
"pid":50448,
"tid":10433558269746414945,
"ts":20795723
}
,
{
"cat":"function",
"dur":61,
"name":"void __cdecl ScrewSandbox::Sandbox::RunLoop(void)",
"ph":"X",
"pid":50448,
"tid":10433558269746414945,
"ts":20795678
}
,
{
"cat":"function",
"dur":15,
"name":"int __cdecl ScrewSandbox::Sandbox::PullEvents(void)",
"ph":"X",
"pid":50448,
"tid":10433558269746414945,
"ts":20795755
}
,
{
"cat":"function",
"dur":16,
"name":"int __cdecl ScrewSandbox::Sandbox::Update(void)",
"ph":"X",
"pid":50448,
"tid":10433558269746414945,
"ts":20795770
}
,
{
"cat":"function",
"dur":15,
"name":"int __cdecl ScrewSandbox::Sandbox::Output(void)",
"ph":"X",
"pid":50448,
"tid":10433558269746414945,
"ts":20795786
}
,
{
"cat":"function",
"dur":63,
"name":"void __cdecl ScrewSandbox::Sandbox::RunLoop(void)",
"ph":"X",
"pid":50448,
"tid":10433558269746414945,
"ts":20795739
}
,
{
"cat":"function",
"dur":16,
"name":"int __cdecl ScrewSandbox::Sandbox::PullEvents(void)",
"ph":"X",
"pid":50448,
"tid":10433558269746414945,
"ts":20795817
}
,
{
"cat":"function",
"dur":16,
"name":"int __cdecl ScrewSandbox::Sandbox::Update(void)",
"ph":"X",
"pid":50448,
"tid":10433558269746414945,
"ts":20795833
}
,
{
"cat":"function",
"dur":16,
"name":"int __cdecl ScrewSandbox::Sandbox::Output(void)",
"ph":"X",
"pid":50448,
"tid":10433558269746414945,
"ts":20795849
}
,
{
"cat":"function",
"dur":63,
"name":"void __cdecl ScrewSandbox::Sandbox::RunLoop(void)",
"ph":"X",
"pid":50448,
"tid":10433558269746414945,
"ts":20795802
}
,
{
"cat":"function",
"dur":16,
"name":"int __cdecl ScrewSandbox::Sandbox::PullEvents(void)",
"ph":"X",
"pid":50448,
"tid":10433558269746414945,
"ts":20795880
}
,
{
"cat":"function",
"dur":15,
"name":"int __cdecl ScrewSandbox::Sandbox::Update(void)",
"ph":"X",
"pid":50448,
"tid":10433558269746414945,
"ts":20795896
}
,
{
"cat":"function",
"dur":16,
"name":"int __cdecl ScrewSandbox::Sandbox::Output(void)",
"ph":"X",
"pid":50448,
"tid":10433558269746414945,
"ts":20795911
}
,
{
"cat":"function",
"dur":62,
"name":"void __cdecl ScrewSandbox::Sandbox::RunLoop(void)",
"ph":"X",
"pid":50448,
"tid":10433558269746414945,
"ts":20795865
}
,
{
"cat":"function",
"dur":15,
"name":"int __cdecl ScrewSandbox::Sandbox::PullEvents(void)",
"ph":"X",
"pid":50448,
"tid":10433558269746414945,
"ts":20795943
}
,
{
"cat":"function",
"dur":16,
"name":"int __cdecl ScrewSandbox::Sandbox::Update(void)",
"ph":"X",
"pid":50448,
"tid":10433558269746414945,
"ts":20795958
}
,
{
"cat":"function",
"dur":15,
"name":"int __cdecl ScrewSandbox::Sandbox::Output(void)",
"ph":"X",
"pid":50448,
"tid":10433558269746414945,
"ts":20795974
}
,
{
"cat":"function",
"dur":62,
"name":"void __cdecl ScrewSandbox::Sandbox::RunLoop(void)",
"ph":"X",
"pid":50448,
"tid":10433558269746414945,
"ts":20795927
}
,
{
"cat":"function",
"dur":16,
"name":"int __cdecl ScrewSandbox::Sandbox::PullEvents(void)",
"ph":"X",
"pid":50448,
"tid":10433558269746414945,
"ts":20796005
}
,
{
"cat":"function",
"dur":15,
"name":"int __cdecl ScrewSandbox::Sandbox::Update(void)",
"ph":"X",
"pid":50448,
"tid":10433558269746414945,
"ts":20796021
}
,
{
"cat":"function",
"dur":16,
"name":"int __cdecl ScrewSandbox::Sandbox::Output(void)",
"ph":"X",
"pid":50448,
"tid":10433558269746414945,
"ts":20796036
}
,
{
"cat":"function",
"dur":64,
"name":"void __cdecl ScrewSandbox::Sandbox::RunLoop(void)",
"ph":"X",
"pid":50448,
"tid":10433558269746414945,
"ts":20795989
}
,
{
"cat":"function",
"dur":15,
"name":"int __cdecl ScrewSandbox::Sandbox::PullEvents(void)",
"ph":"X",
"pid":50448,
"tid":10433558269746414945,
"ts":20796068
}
,
{
"cat":"function",
"dur":16,
"name":"int __cdecl ScrewSandbox::Sandbox::Update(void)",
"ph":"X",
"pid":50448,
"tid":10433558269746414945,
"ts":20796083
}
,
{
"cat":"function",
"dur":16,
"name":"int __cdecl ScrewSandbox::Sandbox::Output(void)",
"ph":"X",
"pid":50448,
"tid":10433558269746414945,
"ts":20796099
}
,
{
"cat":"function",
"dur":62,
"name":"void __cdecl ScrewSandbox::Sandbox::RunLoop(void)",
"ph":"X",
"pid":50448,
"tid":10433558269746414945,
"ts":20796053
}
,
{
"cat":"function",
"dur":16,
"name":"int __cdecl ScrewSandbox::Sandbox::PullEvents(void)",
"ph":"X",
"pid":50448,
"tid":10433558269746414945,
"ts":20796130
}
,
{
"cat":"function",
"dur":16,
"name":"int __cdecl ScrewSandbox::Sandbox::Update(void)",
"ph":"X",
"pid":50448,
"tid":10433558269746414945,
"ts":20796146
}
,
{
"cat":"function",
"dur":15,
"name":"int __cdecl ScrewSandbox::Sandbox::Output(void)",
"ph":"X",
"pid":50448,
"tid":10433558269746414945,
"ts":20796162
}
,
{
"cat":"function",
"dur":62,
"name":"void __cdecl ScrewSandbox::Sandbox::RunLoop(void)",
"ph":"X",
"pid":50448,
"tid":10433558269746414945,
"ts":20796115
}
,
{
"cat":"function",
"dur":15,
"name":"int __cdecl ScrewSandbox::Sandbox::PullEvents(void)",
"ph":"X",
"pid":50448,
"tid":10433558269746414945,
"ts":20796193
}
,
{
"cat":"function",
"dur":15,
"name":"int __cdecl ScrewSandbox::Sandbox::Update(void)",
"ph":"X",
"pid":50448,
"tid":10433558269746414945,
"ts":20796209
}
,
{
"cat":"function",
"dur":16,
"name":"int __cdecl ScrewSandbox::Sandbox::Output(void)",
"ph":"X",
"pid":50448,
"tid":10433558269746414945,
"ts":20796224
}
,
{
"cat":"function",
"dur":63,
"name":"void __cdecl ScrewSandbox::Sandbox::RunLoop(void)",
"ph":"X",
"pid":50448,
"tid":10433558269746414945,
"ts":20796177
}
,
{
"cat":"function",
"dur":15,
"name":"int __cdecl ScrewSandbox::Sandbox::PullEvents(void)",
"ph":"X",
"pid":50448,
"tid":10433558269746414945,
"ts":20796256
}
,
{
"cat":"function",
"dur":16,
"name":"int __cdecl ScrewSandbox::Sandbox::Update(void)",
"ph":"X",
"pid":50448,
"tid":10433558269746414945,
"ts":20796271
}
,
{
"cat":"function",
"dur":15,
"name":"int __cdecl ScrewSandbox::Sandbox::Output(void)",
"ph":"X",
"pid":50448,
"tid":10433558269746414945,
"ts":20796287
}
,
{
"cat":"function",
"dur":62,
"name":"void __cdecl ScrewSandbox::Sandbox::RunLoop(void)",
"ph":"X",
"pid":50448,
"tid":10433558269746414945,
"ts":20796240
}
,
{
"cat":"function",
"dur":16,
"name":"int __cdecl ScrewSandbox::Sandbox::PullEvents(void)",
"ph":"X",
"pid":50448,
"tid":10433558269746414945,
"ts":20796317
}
,
{
"cat":"function",
"dur":15,
"name":"int __cdecl ScrewSandbox::Sandbox::Update(void)",
"ph":"X",
"pid":50448,
"tid":10433558269746414945,
"ts":20796333
}
,
{
"cat":"function",
"dur":16,
"name":"int __cdecl ScrewSandbox::Sandbox::Output(void)",
"ph":"X",
"pid":50448,
"tid":10433558269746414945,
"ts":20796348
}
,
{
"cat":"function",
"dur":62,
"name":"void __cdecl ScrewSandbox::Sandbox::RunLoop(void)",
"ph":"X",
"pid":50448,
"tid":10433558269746414945,
"ts":20796302
}
,
{
"cat":"function",
"dur":15,
"name":"int __cdecl ScrewSandbox::Sandbox::PullEvents(void)",
"ph":"X",
"pid":50448,
"tid":10433558269746414945,
"ts":20796379
}
,
{
"cat":"function",
"dur":15,
"name":"int __cdecl ScrewSandbox::Sandbox::Update(void)",
"ph":"X",
"pid":50448,
"tid":10433558269746414945,
"ts":20796395
}
,
{
"cat":"function",
"dur":15,
"name":"int __cdecl ScrewSandbox::Sandbox::Output(void)",
"ph":"X",
"pid":50448,
"tid":10433558269746414945,
"ts":20796411
}
,
{
"cat":"function",
"dur":62,
"name":"void __cdecl ScrewSandbox::Sandbox::RunLoop(void)",
"ph":"X",
"pid":50448,
"tid":10433558269746414945,
"ts":20796364
}
,
{
"cat":"function",
"dur":16,
"name":"int __cdecl ScrewSandbox::Sandbox::PullEvents(void)",
"ph":"X",
"pid":50448,
"tid":10433558269746414945,
"ts":20796442
}
,
{
"cat":"function",
"dur":16,
"name":"int __cdecl ScrewSandbox::Sandbox::Update(void)",
"ph":"X",
"pid":50448,
"tid":10433558269746414945,
"ts":20796458
}
,
{
"cat":"function",
"dur":15,
"name":"int __cdecl ScrewSandbox::Sandbox::Output(void)",
"ph":"X",
"pid":50448,
"tid":10433558269746414945,
"ts":20796474
}
,
{
"cat":"function",
"dur":64,
"name":"void __cdecl ScrewSandbox::Sandbox::RunLoop(void)",
"ph":"X",
"pid":50448,
"tid":10433558269746414945,
"ts":20796426
}
,
{
"cat":"function",
"dur":16,
"name":"int __cdecl ScrewSandbox::Sandbox::PullEvents(void)",
"ph":"X",
"pid":50448,
"tid":10433558269746414945,
"ts":20796505
}
,
{
"cat":"function",
"dur":16,
"name":"int __cdecl ScrewSandbox::Sandbox::Update(void)",
"ph":"X",
"pid":50448,
"tid":10433558269746414945,
"ts":20796521
}
,
{
"cat":"function",
"dur":16,
"name":"int __cdecl ScrewSandbox::Sandbox::Output(void)",
"ph":"X",
"pid":50448,
"tid":10433558269746414945,
"ts":20796537
}
,
{
"cat":"function",
"dur":63,
"name":"void __cdecl ScrewSandbox::Sandbox::RunLoop(void)",
"ph":"X",
"pid":50448,
"tid":10433558269746414945,
"ts":20796490
}
,
{
"cat":"function",
"dur":15,
"name":"int __cdecl ScrewSandbox::Sandbox::PullEvents(void)",
"ph":"X",
"pid":50448,
"tid":10433558269746414945,
"ts":20796568
}
,
{
"cat":"function",
"dur":16,
"name":"int __cdecl ScrewSandbox::Sandbox::Update(void)",
"ph":"X",
"pid":50448,
"tid":10433558269746414945,
"ts":20796583
}
,
{
"cat":"function",
"dur":16,
"name":"int __cdecl ScrewSandbox::Sandbox::Output(void)",
"ph":"X",
"pid":50448,
"tid":10433558269746414945,
"ts":20796599
}
,
{
"cat":"function",
"dur":62,
"name":"void __cdecl ScrewSandbox::Sandbox::RunLoop(void)",
"ph":"X",
"pid":50448,
"tid":10433558269746414945,
"ts":20796553
}
,
{
"cat":"function",
"dur":15,
"name":"int __cdecl ScrewSandbox::Sandbox::PullEvents(void)",
"ph":"X",
"pid":50448,
"tid":10433558269746414945,
"ts":20796631
}
,
{
"cat":"function",
"dur":15,
"name":"int __cdecl ScrewSandbox::Sandbox::Update(void)",
"ph":"X",
"pid":50448,
"tid":10433558269746414945,
"ts":20796646
}
,
{
"cat":"function",
"dur":16,
"name":"int __cdecl ScrewSandbox::Sandbox::Output(void)",
"ph":"X",
"pid":50448,
"tid":10433558269746414945,
"ts":20796662
}
,
{
"cat":"function",
"dur":63,
"name":"void __cdecl ScrewSandbox::Sandbox::RunLoop(void)",
"ph":"X",
"pid":50448,
"tid":10433558269746414945,
"ts":20796615
}
,
{
"cat":"function",
"dur":16,
"name":"int __cdecl ScrewSandbox::Sandbox::PullEvents(void)",
"ph":"X",
"pid":50448,
"tid":10433558269746414945,
"ts":20796693
}
,
{
"cat":"function",
"dur":16,
"name":"int __cdecl ScrewSandbox::Sandbox::Update(void)",
"ph":"X",
"pid":50448,
"tid":10433558269746414945,
"ts":20796709
}
,
{
"cat":"function",
"dur":15,
"name":"int __cdecl ScrewSandbox::Sandbox::Output(void)",
"ph":"X",
"pid":50448,
"tid":10433558269746414945,
"ts":20796725
}
,
{
"cat":"function",
"dur":62,
"name":"void __cdecl ScrewSandbox::Sandbox::RunLoop(void)",
"ph":"X",
"pid":50448,
"tid":10433558269746414945,
"ts":20796678
}
,
{
"cat":"function",
"dur":16,
"name":"int __cdecl ScrewSandbox::Sandbox::PullEvents(void)",
"ph":"X",
"pid":50448,
"tid":10433558269746414945,
"ts":20796756
}
,
{
"cat":"function",
"dur":15,
"name":"int __cdecl ScrewSandbox::Sandbox::Update(void)",
"ph":"X",
"pid":50448,
"tid":10433558269746414945,
"ts":20796772
}
,
{
"cat":"function",
"dur":16,
"name":"int __cdecl ScrewSandbox::Sandbox::Output(void)",
"ph":"X",
"pid":50448,
"tid":10433558269746414945,
"ts":20796787
}
,
{
"cat":"function",
"dur":62,
"name":"void __cdecl ScrewSandbox::Sandbox::RunLoop(void)",
"ph":"X",
"pid":50448,
"tid":10433558269746414945,
"ts":20796741
}
,
{
"cat":"function",
"dur":16,
"name":"int __cdecl ScrewSandbox::Sandbox::PullEvents(void)",
"ph":"X",
"pid":50448,
"tid":10433558269746414945,
"ts":20796819
}
,
{
"cat":"function",
"dur":16,
"name":"int __cdecl ScrewSandbox::Sandbox::Update(void)",
"ph":"X",
"pid":50448,
"tid":10433558269746414945,
"ts":20796835
}
,
{
"cat":"function",
"dur":15,
"name":"int __cdecl ScrewSandbox::Sandbox::Output(void)",
"ph":"X",
"pid":50448,
"tid":10433558269746414945,
"ts":20796851
}
,
{
"cat":"function",
"dur":62,
"name":"void __cdecl ScrewSandbox::Sandbox::RunLoop(void)",
"ph":"X",
"pid":50448,
"tid":10433558269746414945,
"ts":20796804
}
,
{
"cat":"function",
"dur":15,
"name":"int __cdecl ScrewSandbox::Sandbox::PullEvents(void)",
"ph":"X",
"pid":50448,
"tid":10433558269746414945,
"ts":20796881
}
,
{
"cat":"function",
"dur":16,
"name":"int __cdecl ScrewSandbox::Sandbox::Update(void)",
"ph":"X",
"pid":50448,
"tid":10433558269746414945,
"ts":20796897
}
,
{
"cat":"function",
"dur":15,
"name":"int __cdecl ScrewSandbox::Sandbox::Output(void)",
"ph":"X",
"pid":50448,
"tid":10433558269746414945,
"ts":20796913
}
,
{
"cat":"function",
"dur":62,
"name":"void __cdecl ScrewSandbox::Sandbox::RunLoop(void)",
"ph":"X",
"pid":50448,
"tid":10433558269746414945,
"ts":20796866
}
,
{
"cat":"function",
"dur":15,
"name":"int __cdecl ScrewSandbox::Sandbox::PullEvents(void)",
"ph":"X",
"pid":50448,
"tid":10433558269746414945,
"ts":20796944
}
,
{
"cat":"function",
"dur":16,
"name":"int __cdecl ScrewSandbox::Sandbox::Update(void)",
"ph":"X",
"pid":50448,
"tid":10433558269746414945,
"ts":20796959
}
,
{
"cat":"function",
"dur":16,
"name":"int __cdecl ScrewSandbox::Sandbox::Output(void)",
"ph":"X",
"pid":50448,
"tid":10433558269746414945,
"ts":20796975
}
,
{
"cat":"function",
"dur":63,
"name":"void __cdecl ScrewSandbox::Sandbox::RunLoop(void)",
"ph":"X",
"pid":50448,
"tid":10433558269746414945,
"ts":20796928
}
,
{
"cat":"function",
"dur":15,
"name":"int __cdecl ScrewSandbox::Sandbox::PullEvents(void)",
"ph":"X",
"pid":50448,
"tid":10433558269746414945,
"ts":20797007
}
,
{
"cat":"function",
"dur":15,
"name":"int __cdecl ScrewSandbox::Sandbox::Update(void)",
"ph":"X",
"pid":50448,
"tid":10433558269746414945,
"ts":20797023
}
,
{
"cat":"function",
"dur":15,
"name":"int __cdecl ScrewSandbox::Sandbox::Output(void)",
"ph":"X",
"pid":50448,
"tid":10433558269746414945,
"ts":20797038
}
,
{
"cat":"function",
"dur":63,
"name":"void __cdecl ScrewSandbox::Sandbox::RunLoop(void)",
"ph":"X",
"pid":50448,
"tid":10433558269746414945,
"ts":20796991
}
,
{
"cat":"function",
"dur":15,
"name":"int __cdecl ScrewSandbox::Sandbox::PullEvents(void)",
"ph":"X",
"pid":50448,
"tid":10433558269746414945,
"ts":20797070
}
,
{
"cat":"function",
"dur":16,
"name":"int __cdecl ScrewSandbox::Sandbox::Update(void)",
"ph":"X",
"pid":50448,
"tid":10433558269746414945,
"ts":20797085
}
,
{
"cat":"function",
"dur":16,
"name":"int __cdecl ScrewSandbox::Sandbox::Output(void)",
"ph":"X",
"pid":50448,
"tid":10433558269746414945,
"ts":20797101
}
,
{
"cat":"function",
"dur":63,
"name":"void __cdecl ScrewSandbox::Sandbox::RunLoop(void)",
"ph":"X",
"pid":50448,
"tid":10433558269746414945,
"ts":20797054
}
,
{
"cat":"function",
"dur":16,
"name":"int __cdecl ScrewSandbox::Sandbox::PullEvents(void)",
"ph":"X",
"pid":50448,
"tid":10433558269746414945,
"ts":20797133
}
,
{
"cat":"function",
"dur":14,
"name":"int __cdecl ScrewSandbox::Sandbox::Update(void)",
"ph":"X",
"pid":50448,
"tid":10433558269746414945,
"ts":20797149
}
,
{
"cat":"function",
"dur":15,
"name":"int __cdecl ScrewSandbox::Sandbox::Output(void)",
"ph":"X",
"pid":50448,
"tid":10433558269746414945,
"ts":20797164
}
,
{
"cat":"function",
"dur":62,
"name":"void __cdecl ScrewSandbox::Sandbox::RunLoop(void)",
"ph":"X",
"pid":50448,
"tid":10433558269746414945,
"ts":20797117
}
,
{
"cat":"function",
"dur":15,
"name":"int __cdecl ScrewSandbox::Sandbox::PullEvents(void)",
"ph":"X",
"pid":50448,
"tid":10433558269746414945,
"ts":20797195
}
,
{
"cat":"function",
"dur":15,
"name":"int __cdecl ScrewSandbox::Sandbox::Update(void)",
"ph":"X",
"pid":50448,
"tid":10433558269746414945,
"ts":20797210
}
,
{
"cat":"function",
"dur":16,
"name":"int __cdecl ScrewSandbox::Sandbox::Output(void)",
"ph":"X",
"pid":50448,
"tid":10433558269746414945,
"ts":20797225
}
,
{
"cat":"function",
"dur":62,
"name":"void __cdecl ScrewSandbox::Sandbox::RunLoop(void)",
"ph":"X",
"pid":50448,
"tid":10433558269746414945,
"ts":20797179
}
,
{
"cat":"function",
"dur":15,
"name":"int __cdecl ScrewSandbox::Sandbox::PullEvents(void)",
"ph":"X",
"pid":50448,
"tid":10433558269746414945,
"ts":20797257
}
,
{
"cat":"function",
"dur":15,
"name":"int __cdecl ScrewSandbox::Sandbox::Update(void)",
"ph":"X",
"pid":50448,
"tid":10433558269746414945,
"ts":20797273
}
,
{
"cat":"function",
"dur":15,
"name":"int __cdecl ScrewSandbox::Sandbox::Output(void)",
"ph":"X",
"pid":50448,
"tid":10433558269746414945,
"ts":20797288
}
,
{
"cat":"function",
"dur":62,
"name":"void __cdecl ScrewSandbox::Sandbox::RunLoop(void)",
"ph":"X",
"pid":50448,
"tid":10433558269746414945,
"ts":20797241
}
,
{
"cat":"function",
"dur":15,
"name":"int __cdecl ScrewSandbox::Sandbox::PullEvents(void)",
"ph":"X",
"pid":50448,
"tid":10433558269746414945,
"ts":20797319
}
,
{
"cat":"function",
"dur":15,
"name":"int __cdecl ScrewSandbox::Sandbox::Update(void)",
"ph":"X",
"pid":50448,
"tid":10433558269746414945,
"ts":20797334
}
,
{
"cat":"function",
"dur":16,
"name":"int __cdecl ScrewSandbox::Sandbox::Output(void)",
"ph":"X",
"pid":50448,
"tid":10433558269746414945,
"ts":20797349
}
,
{
"cat":"function",
"dur":63,
"name":"void __cdecl ScrewSandbox::Sandbox::RunLoop(void)",
"ph":"X",
"pid":50448,
"tid":10433558269746414945,
"ts":20797303
}
,
{
"cat":"function",
"dur":16,
"name":"int __cdecl ScrewSandbox::Sandbox::PullEvents(void)",
"ph":"X",
"pid":50448,
"tid":10433558269746414945,
"ts":20797381
}
,
{
"cat":"function",
"dur":16,
"name":"int __cdecl ScrewSandbox::Sandbox::Update(void)",
"ph":"X",
"pid":50448,
"tid":10433558269746414945,
"ts":20797397
}
,
{
"cat":"function",
"dur":16,
"name":"int __cdecl ScrewSandbox::Sandbox::Output(void)",
"ph":"X",
"pid":50448,
"tid":10433558269746414945,
"ts":20797413
}
,
{
"cat":"function",
"dur":63,
"name":"void __cdecl ScrewSandbox::Sandbox::RunLoop(void)",
"ph":"X",
"pid":50448,
"tid":10433558269746414945,
"ts":20797366
}
,
{
"cat":"function",
"dur":15,
"name":"int __cdecl ScrewSandbox::Sandbox::PullEvents(void)",
"ph":"X",
"pid":50448,
"tid":10433558269746414945,
"ts":20797444
}
,
{
"cat":"function",
"dur":16,
"name":"int __cdecl ScrewSandbox::Sandbox::Update(void)",
"ph":"X",
"pid":50448,
"tid":10433558269746414945,
"ts":20797459
}
,
{
"cat":"function",
"dur":15,
"name":"int __cdecl ScrewSandbox::Sandbox::Output(void)",
"ph":"X",
"pid":50448,
"tid":10433558269746414945,
"ts":20797475
}
,
{
"cat":"function",
"dur":61,
"name":"void __cdecl ScrewSandbox::Sandbox::RunLoop(void)",
"ph":"X",
"pid":50448,
"tid":10433558269746414945,
"ts":20797429
}
,
{
"cat":"function",
"dur":16,
"name":"int __cdecl ScrewSandbox::Sandbox::PullEvents(void)",
"ph":"X",
"pid":50448,
"tid":10433558269746414945,
"ts":20797506
}
,
{
"cat":"function",
"dur":15,
"name":"int __cdecl ScrewSandbox::Sandbox::Update(void)",
"ph":"X",
"pid":50448,
"tid":10433558269746414945,
"ts":20797522
}
,
{
"cat":"function",
"dur":15,
"name":"int __cdecl ScrewSandbox::Sandbox::Output(void)",
"ph":"X",
"pid":50448,
"tid":10433558269746414945,
"ts":20797538
}
,
{
"cat":"function",
"dur":63,
"name":"void __cdecl ScrewSandbox::Sandbox::RunLoop(void)",
"ph":"X",
"pid":50448,
"tid":10433558269746414945,
"ts":20797491
}
,
{
"cat":"function",
"dur":16,
"name":"int __cdecl ScrewSandbox::Sandbox::PullEvents(void)",
"ph":"X",
"pid":50448,
"tid":10433558269746414945,
"ts":20797569
}
,
{
"cat":"function",
"dur":15,
"name":"int __cdecl ScrewSandbox::Sandbox::Update(void)",
"ph":"X",
"pid":50448,
"tid":10433558269746414945,
"ts":20797585
}
,
{
"cat":"function",
"dur":16,
"name":"int __cdecl ScrewSandbox::Sandbox::Output(void)",
"ph":"X",
"pid":50448,
"tid":10433558269746414945,
"ts":20797600
}
,
{
"cat":"function",
"dur":62,
"name":"void __cdecl ScrewSandbox::Sandbox::RunLoop(void)",
"ph":"X",
"pid":50448,
"tid":10433558269746414945,
"ts":20797554
}
,
{
"cat":"function",
"dur":15,
"name":"int __cdecl ScrewSandbox::Sandbox::PullEvents(void)",
"ph":"X",
"pid":50448,
"tid":10433558269746414945,
"ts":20797632
}
,
{
"cat":"function",
"dur":16,
"name":"int __cdecl ScrewSandbox::Sandbox::Update(void)",
"ph":"X",
"pid":50448,
"tid":10433558269746414945,
"ts":20797647
}
,
{
"cat":"function",
"dur":15,
"name":"int __cdecl ScrewSandbox::Sandbox::Output(void)",
"ph":"X",
"pid":50448,
"tid":10433558269746414945,
"ts":20797664
}
,
{
"cat":"function",
"dur":63,
"name":"void __cdecl ScrewSandbox::Sandbox::RunLoop(void)",
"ph":"X",
"pid":50448,
"tid":10433558269746414945,
"ts":20797616
}
,
{
"cat":"function",
"dur":15,
"name":"int __cdecl ScrewSandbox::Sandbox::PullEvents(void)",
"ph":"X",
"pid":50448,
"tid":10433558269746414945,
"ts":20797695
}
,
{
"cat":"function",
"dur":15,
"name":"int __cdecl ScrewSandbox::Sandbox::Update(void)",
"ph":"X",
"pid":50448,
"tid":10433558269746414945,
"ts":20797710
}
,
{
"cat":"function",
"dur":16,
"name":"int __cdecl ScrewSandbox::Sandbox::Output(void)",
"ph":"X",
"pid":50448,
"tid":10433558269746414945,
"ts":20797725
}
,
{
"cat":"function",
"dur":62,
"name":"void __cdecl ScrewSandbox::Sandbox::RunLoop(void)",
"ph":"X",
"pid":50448,
"tid":10433558269746414945,
"ts":20797679
}
,
{
"cat":"function",
"dur":15,
"name":"int __cdecl ScrewSandbox::Sandbox::PullEvents(void)",
"ph":"X",
"pid":50448,
"tid":10433558269746414945,
"ts":20797757
}
,
{
"cat":"function",
"dur":16,
"name":"int __cdecl ScrewSandbox::Sandbox::Update(void)",
"ph":"X",
"pid":50448,
"tid":10433558269746414945,
"ts":20797772
}
,
{
"cat":"function",
"dur":15,
"name":"int __cdecl ScrewSandbox::Sandbox::Output(void)",
"ph":"X",
"pid":50448,
"tid":10433558269746414945,
"ts":20797788
}
,
{
"cat":"function",
"dur":63,
"name":"void __cdecl ScrewSandbox::Sandbox::RunLoop(void)",
"ph":"X",
"pid":50448,
"tid":10433558269746414945,
"ts":20797741
}
,
{
"cat":"function",
"dur":15,
"name":"int __cdecl ScrewSandbox::Sandbox::PullEvents(void)",
"ph":"X",
"pid":50448,
"tid":10433558269746414945,
"ts":20797819
}
,
{
"cat":"function",
"dur":15,
"name":"int __cdecl ScrewSandbox::Sandbox::Update(void)",
"ph":"X",
"pid":50448,
"tid":10433558269746414945,
"ts":20797834
}
,
{
"cat":"function",
"dur":15,
"name":"int __cdecl ScrewSandbox::Sandbox::Output(void)",
"ph":"X",
"pid":50448,
"tid":10433558269746414945,
"ts":20797850
}
,
{
"cat":"function",
"dur":61,
"name":"void __cdecl ScrewSandbox::Sandbox::RunLoop(void)",
"ph":"X",
"pid":50448,
"tid":10433558269746414945,
"ts":20797804
}
,
{
"cat":"function",
"dur":16,
"name":"int __cdecl ScrewSandbox::Sandbox::PullEvents(void)",
"ph":"X",
"pid":50448,
"tid":10433558269746414945,
"ts":20797881
}
,
{
"cat":"function",
"dur":16,
"name":"int __cdecl ScrewSandbox::Sandbox::Update(void)",
"ph":"X",
"pid":50448,
"tid":10433558269746414945,
"ts":20797897
}
,
{
"cat":"function",
"dur":15,
"name":"int __cdecl ScrewSandbox::Sandbox::Output(void)",
"ph":"X",
"pid":50448,
"tid":10433558269746414945,
"ts":20797913
}
,
{
"cat":"function",
"dur":63,
"name":"void __cdecl ScrewSandbox::Sandbox::RunLoop(void)",
"ph":"X",
"pid":50448,
"tid":10433558269746414945,
"ts":20797865
}
,
{
"cat":"function",
"dur":16,
"name":"int __cdecl ScrewSandbox::Sandbox::PullEvents(void)",
"ph":"X",
"pid":50448,
"tid":10433558269746414945,
"ts":20797943
}
,
{
"cat":"function",
"dur":16,
"name":"int __cdecl ScrewSandbox::Sandbox::Update(void)",
"ph":"X",
"pid":50448,
"tid":10433558269746414945,
"ts":20797959
}
,
{
"cat":"function",
"dur":15,
"name":"int __cdecl ScrewSandbox::Sandbox::Output(void)",
"ph":"X",
"pid":50448,
"tid":10433558269746414945,
"ts":20797975
}
,
{
"cat":"function",
"dur":62,
"name":"void __cdecl ScrewSandbox::Sandbox::RunLoop(void)",
"ph":"X",
"pid":50448,
"tid":10433558269746414945,
"ts":20797928
}
,
{
"cat":"function",
"dur":16,
"name":"int __cdecl ScrewSandbox::Sandbox::PullEvents(void)",
"ph":"X",
"pid":50448,
"tid":10433558269746414945,
"ts":20798006
}
,
{
"cat":"function",
"dur":15,
"name":"int __cdecl ScrewSandbox::Sandbox::Update(void)",
"ph":"X",
"pid":50448,
"tid":10433558269746414945,
"ts":20798022
}
,
{
"cat":"function",
"dur":15,
"name":"int __cdecl ScrewSandbox::Sandbox::Output(void)",
"ph":"X",
"pid":50448,
"tid":10433558269746414945,
"ts":20798038
}
,
{
"cat":"function",
"dur":64,
"name":"void __cdecl ScrewSandbox::Sandbox::RunLoop(void)",
"ph":"X",
"pid":50448,
"tid":10433558269746414945,
"ts":20797990
}
,
{
"cat":"function",
"dur":16,
"name":"int __cdecl ScrewSandbox::Sandbox::PullEvents(void)",
"ph":"X",
"pid":50448,
"tid":10433558269746414945,
"ts":20798069
}
,
{
"cat":"function",
"dur":16,
"name":"int __cdecl ScrewSandbox::Sandbox::Update(void)",
"ph":"X",
"pid":50448,
"tid":10433558269746414945,
"ts":20798085
}
,
{
"cat":"function",
"dur":16,
"name":"int __cdecl ScrewSandbox::Sandbox::Output(void)",
"ph":"X",
"pid":50448,
"tid":10433558269746414945,
"ts":20798101
}
,
{
"cat":"function",
"dur":63,
"name":"void __cdecl ScrewSandbox::Sandbox::RunLoop(void)",
"ph":"X",
"pid":50448,
"tid":10433558269746414945,
"ts":20798054
}
,
{
"cat":"function",
"dur":16,
"name":"int __cdecl ScrewSandbox::Sandbox::PullEvents(void)",
"ph":"X",
"pid":50448,
"tid":10433558269746414945,
"ts":20798132
}
,
{
"cat":"function",
"dur":16,
"name":"int __cdecl ScrewSandbox::Sandbox::Update(void)",
"ph":"X",
"pid":50448,
"tid":10433558269746414945,
"ts":20798148
}
,
{
"cat":"function",
"dur":16,
"name":"int __cdecl ScrewSandbox::Sandbox::Output(void)",
"ph":"X",
"pid":50448,
"tid":10433558269746414945,
"ts":20798164
}
,
{
"cat":"function",
"dur":63,
"name":"void __cdecl ScrewSandbox::Sandbox::RunLoop(void)",
"ph":"X",
"pid":50448,
"tid":10433558269746414945,
"ts":20798117
}
,
{
"cat":"function",
"dur":15,
"name":"int __cdecl ScrewSandbox::Sandbox::PullEvents(void)",
"ph":"X",
"pid":50448,
"tid":10433558269746414945,
"ts":20798196
}
,
{
"cat":"function",
"dur":16,
"name":"int __cdecl ScrewSandbox::Sandbox::Update(void)",
"ph":"X",
"pid":50448,
"tid":10433558269746414945,
"ts":20798212
}
,
{
"cat":"function",
"dur":16,
"name":"int __cdecl ScrewSandbox::Sandbox::Output(void)",
"ph":"X",
"pid":50448,
"tid":10433558269746414945,
"ts":20798228
}
,
{
"cat":"function",
"dur":64,
"name":"void __cdecl ScrewSandbox::Sandbox::RunLoop(void)",
"ph":"X",
"pid":50448,
"tid":10433558269746414945,
"ts":20798180
}
,
{
"cat":"function",
"dur":15,
"name":"int __cdecl ScrewSandbox::Sandbox::PullEvents(void)",
"ph":"X",
"pid":50448,
"tid":10433558269746414945,
"ts":20798260
}
,
{
"cat":"function",
"dur":16,
"name":"int __cdecl ScrewSandbox::Sandbox::Update(void)",
"ph":"X",
"pid":50448,
"tid":10433558269746414945,
"ts":20798275
}
,
{
"cat":"function",
"dur":15,
"name":"int __cdecl ScrewSandbox::Sandbox::Output(void)",
"ph":"X",
"pid":50448,
"tid":10433558269746414945,
"ts":20798291
}
,
{
"cat":"function",
"dur":62,
"name":"void __cdecl ScrewSandbox::Sandbox::RunLoop(void)",
"ph":"X",
"pid":50448,
"tid":10433558269746414945,
"ts":20798244
}
,
{
"cat":"function",
"dur":16,
"name":"int __cdecl ScrewSandbox::Sandbox::PullEvents(void)",
"ph":"X",
"pid":50448,
"tid":10433558269746414945,
"ts":20798321
}
,
{
"cat":"function",
"dur":16,
"name":"int __cdecl ScrewSandbox::Sandbox::Update(void)",
"ph":"X",
"pid":50448,
"tid":10433558269746414945,
"ts":20798337
}
,
{
"cat":"function",
"dur":15,
"name":"int __cdecl ScrewSandbox::Sandbox::Output(void)",
"ph":"X",
"pid":50448,
"tid":10433558269746414945,
"ts":20798353
}
,
{
"cat":"function",
"dur":63,
"name":"void __cdecl ScrewSandbox::Sandbox::RunLoop(void)",
"ph":"X",
"pid":50448,
"tid":10433558269746414945,
"ts":20798306
}
,
{
"cat":"function",
"dur":15,
"name":"int __cdecl ScrewSandbox::Sandbox::PullEvents(void)",
"ph":"X",
"pid":50448,
"tid":10433558269746414945,
"ts":20798385
}
,
{
"cat":"function",
"dur":15,
"name":"int __cdecl ScrewSandbox::Sandbox::Update(void)",
"ph":"X",
"pid":50448,
"tid":10433558269746414945,
"ts":20798400
}
,
{
"cat":"function",
"dur":16,
"name":"int __cdecl ScrewSandbox::Sandbox::Output(void)",
"ph":"X",
"pid":50448,
"tid":10433558269746414945,
"ts":20798415
}
,
{
"cat":"function",
"dur":62,
"name":"void __cdecl ScrewSandbox::Sandbox::RunLoop(void)",
"ph":"X",
"pid":50448,
"tid":10433558269746414945,
"ts":20798369
}
,
{
"cat":"function",
"dur":16,
"name":"int __cdecl ScrewSandbox::Sandbox::PullEvents(void)",
"ph":"X",
"pid":50448,
"tid":10433558269746414945,
"ts":20798446
}
,
{
"cat":"function",
"dur":16,
"name":"int __cdecl ScrewSandbox::Sandbox::Update(void)",
"ph":"X",
"pid":50448,
"tid":10433558269746414945,
"ts":20798462
}
,
{
"cat":"function",
"dur":15,
"name":"int __cdecl ScrewSandbox::Sandbox::Output(void)",
"ph":"X",
"pid":50448,
"tid":10433558269746414945,
"ts":20798478
}
,
{
"cat":"function",
"dur":62,
"name":"void __cdecl ScrewSandbox::Sandbox::RunLoop(void)",
"ph":"X",
"pid":50448,
"tid":10433558269746414945,
"ts":20798431
}
,
{
"cat":"function",
"dur":16,
"name":"int __cdecl ScrewSandbox::Sandbox::PullEvents(void)",
"ph":"X",
"pid":50448,
"tid":10433558269746414945,
"ts":20798509
}
,
{
"cat":"function",
"dur":15,
"name":"int __cdecl ScrewSandbox::Sandbox::Update(void)",
"ph":"X",
"pid":50448,
"tid":10433558269746414945,
"ts":20798525
}
,
{
"cat":"function",
"dur":16,
"name":"int __cdecl ScrewSandbox::Sandbox::Output(void)",
"ph":"X",
"pid":50448,
"tid":10433558269746414945,
"ts":20798540
}
,
{
"cat":"function",
"dur":62,
"name":"void __cdecl ScrewSandbox::Sandbox::RunLoop(void)",
"ph":"X",
"pid":50448,
"tid":10433558269746414945,
"ts":20798494
}
,
{
"cat":"function",
"dur":15,
"name":"int __cdecl ScrewSandbox::Sandbox::PullEvents(void)",
"ph":"X",
"pid":50448,
"tid":10433558269746414945,
"ts":20798572
}
,
{
"cat":"function",
"dur":16,
"name":"int __cdecl ScrewSandbox::Sandbox::Update(void)",
"ph":"X",
"pid":50448,
"tid":10433558269746414945,
"ts":20798587
}
,
{
"cat":"function",
"dur":16,
"name":"int __cdecl ScrewSandbox::Sandbox::Output(void)",
"ph":"X",
"pid":50448,
"tid":10433558269746414945,
"ts":20798603
}
,
{
"cat":"function",
"dur":63,
"name":"void __cdecl ScrewSandbox::Sandbox::RunLoop(void)",
"ph":"X",
"pid":50448,
"tid":10433558269746414945,
"ts":20798556
}
,
{
"cat":"function",
"dur":15,
"name":"int __cdecl ScrewSandbox::Sandbox::PullEvents(void)",
"ph":"X",
"pid":50448,
"tid":10433558269746414945,
"ts":20798635
}
,
{
"cat":"function",
"dur":15,
"name":"int __cdecl ScrewSandbox::Sandbox::Update(void)",
"ph":"X",
"pid":50448,
"tid":10433558269746414945,
"ts":20798651
}
,
{
"cat":"function",
"dur":15,
"name":"int __cdecl ScrewSandbox::Sandbox::Output(void)",
"ph":"X",
"pid":50448,
"tid":10433558269746414945,
"ts":20798666
}
,
{
"cat":"function",
"dur":62,
"name":"void __cdecl ScrewSandbox::Sandbox::RunLoop(void)",
"ph":"X",
"pid":50448,
"tid":10433558269746414945,
"ts":20798619
}
,
{
"cat":"function",
"dur":16,
"name":"int __cdecl ScrewSandbox::Sandbox::PullEvents(void)",
"ph":"X",
"pid":50448,
"tid":10433558269746414945,
"ts":20798697
}
,
{
"cat":"function",
"dur":15,
"name":"int __cdecl ScrewSandbox::Sandbox::Update(void)",
"ph":"X",
"pid":50448,
"tid":10433558269746414945,
"ts":20798713
}
,
{
"cat":"function",
"dur":16,
"name":"int __cdecl ScrewSandbox::Sandbox::Output(void)",
"ph":"X",
"pid":50448,
"tid":10433558269746414945,
"ts":20798728
}
,
{
"cat":"function",
"dur":63,
"name":"void __cdecl ScrewSandbox::Sandbox::RunLoop(void)",
"ph":"X",
"pid":50448,
"tid":10433558269746414945,
"ts":20798681
}
,
{
"cat":"function",
"dur":15,
"name":"int __cdecl ScrewSandbox::Sandbox::PullEvents(void)",
"ph":"X",
"pid":50448,
"tid":10433558269746414945,
"ts":20798760
}
,
{
"cat":"function",
"dur":15,
"name":"int __cdecl ScrewSandbox::Sandbox::Update(void)",
"ph":"X",
"pid":50448,
"tid":10433558269746414945,
"ts":20798776
}
,
{
"cat":"function",
"dur":16,
"name":"int __cdecl ScrewSandbox::Sandbox::Output(void)",
"ph":"X",
"pid":50448,
"tid":10433558269746414945,
"ts":20798791
}
,
{
"cat":"function",
"dur":63,
"name":"void __cdecl ScrewSandbox::Sandbox::RunLoop(void)",
"ph":"X",
"pid":50448,
"tid":10433558269746414945,
"ts":20798744
}
,
{
"cat":"function",
"dur":15,
"name":"int __cdecl ScrewSandbox::Sandbox::PullEvents(void)",
"ph":"X",
"pid":50448,
"tid":10433558269746414945,
"ts":20798823
}
,
{
"cat":"function",
"dur":16,
"name":"int __cdecl ScrewSandbox::Sandbox::Update(void)",
"ph":"X",
"pid":50448,
"tid":10433558269746414945,
"ts":20798838
}
,
{
"cat":"function",
"dur":16,
"name":"int __cdecl ScrewSandbox::Sandbox::Output(void)",
"ph":"X",
"pid":50448,
"tid":10433558269746414945,
"ts":20798854
}
,
{
"cat":"function",
"dur":63,
"name":"void __cdecl ScrewSandbox::Sandbox::RunLoop(void)",
"ph":"X",
"pid":50448,
"tid":10433558269746414945,
"ts":20798807
}
,
{
"cat":"function",
"dur":16,
"name":"int __cdecl ScrewSandbox::Sandbox::PullEvents(void)",
"ph":"X",
"pid":50448,
"tid":10433558269746414945,
"ts":20798885
}
,
{
"cat":"function",
"dur":15,
"name":"int __cdecl ScrewSandbox::Sandbox::Update(void)",
"ph":"X",
"pid":50448,
"tid":10433558269746414945,
"ts":20798901
}
,
{
"cat":"function",
"dur":15,
"name":"int __cdecl ScrewSandbox::Sandbox::Output(void)",
"ph":"X",
"pid":50448,
"tid":10433558269746414945,
"ts":20798916
}
,
{
"cat":"function",
"dur":61,
"name":"void __cdecl ScrewSandbox::Sandbox::RunLoop(void)",
"ph":"X",
"pid":50448,
"tid":10433558269746414945,
"ts":20798870
}
,
{
"cat":"function",
"dur":15,
"name":"int __cdecl ScrewSandbox::Sandbox::PullEvents(void)",
"ph":"X",
"pid":50448,
"tid":10433558269746414945,
"ts":20798947
}
,
{
"cat":"function",
"dur":15,
"name":"int __cdecl ScrewSandbox::Sandbox::Update(void)",
"ph":"X",
"pid":50448,
"tid":10433558269746414945,
"ts":20798962
}
,
{
"cat":"function",
"dur":15,
"name":"int __cdecl ScrewSandbox::Sandbox::Output(void)",
"ph":"X",
"pid":50448,
"tid":10433558269746414945,
"ts":20798978
}
,
{
"cat":"function",
"dur":62,
"name":"void __cdecl ScrewSandbox::Sandbox::RunLoop(void)",
"ph":"X",
"pid":50448,
"tid":10433558269746414945,
"ts":20798931
}
,
{
"cat":"function",
"dur":15,
"name":"int __cdecl ScrewSandbox::Sandbox::PullEvents(void)",
"ph":"X",
"pid":50448,
"tid":10433558269746414945,
"ts":20799009
}
,
{
"cat":"function",
"dur":15,
"name":"int __cdecl ScrewSandbox::Sandbox::Update(void)",
"ph":"X",
"pid":50448,
"tid":10433558269746414945,
"ts":20799025
}
,
{
"cat":"function",
"dur":16,
"name":"int __cdecl ScrewSandbox::Sandbox::Output(void)",
"ph":"X",
"pid":50448,
"tid":10433558269746414945,
"ts":20799040
}
,
{
"cat":"function",
"dur":63,
"name":"void __cdecl ScrewSandbox::Sandbox::RunLoop(void)",
"ph":"X",
"pid":50448,
"tid":10433558269746414945,
"ts":20798993
}
,
{
"cat":"function",
"dur":15,
"name":"int __cdecl ScrewSandbox::Sandbox::PullEvents(void)",
"ph":"X",
"pid":50448,
"tid":10433558269746414945,
"ts":20799071
}
,
{
"cat":"function",
"dur":15,
"name":"int __cdecl ScrewSandbox::Sandbox::Update(void)",
"ph":"X",
"pid":50448,
"tid":10433558269746414945,
"ts":20799086
}
,
{
"cat":"function",
"dur":16,
"name":"int __cdecl ScrewSandbox::Sandbox::Output(void)",
"ph":"X",
"pid":50448,
"tid":10433558269746414945,
"ts":20799101
}
,
{
"cat":"function",
"dur":61,
"name":"void __cdecl ScrewSandbox::Sandbox::RunLoop(void)",
"ph":"X",
"pid":50448,
"tid":10433558269746414945,
"ts":20799056
}
,
{
"cat":"function",
"dur":15,
"name":"int __cdecl ScrewSandbox::Sandbox::PullEvents(void)",
"ph":"X",
"pid":50448,
"tid":10433558269746414945,
"ts":20799133
}
,
{
"cat":"function",
"dur":15,
"name":"int __cdecl ScrewSandbox::Sandbox::Update(void)",
"ph":"X",
"pid":50448,
"tid":10433558269746414945,
"ts":20799149
}
,
{
"cat":"function",
"dur":15,
"name":"int __cdecl ScrewSandbox::Sandbox::Output(void)",
"ph":"X",
"pid":50448,
"tid":10433558269746414945,
"ts":20799165
}
,
{
"cat":"function",
"dur":63,
"name":"void __cdecl ScrewSandbox::Sandbox::RunLoop(void)",
"ph":"X",
"pid":50448,
"tid":10433558269746414945,
"ts":20799117
}
,
{
"cat":"function",
"dur":15,
"name":"int __cdecl ScrewSandbox::Sandbox::PullEvents(void)",
"ph":"X",
"pid":50448,
"tid":10433558269746414945,
"ts":20799196
}
,
{
"cat":"function",
"dur":16,
"name":"int __cdecl ScrewSandbox::Sandbox::Update(void)",
"ph":"X",
"pid":50448,
"tid":10433558269746414945,
"ts":20799211
}
,
{
"cat":"function",
"dur":15,
"name":"int __cdecl ScrewSandbox::Sandbox::Output(void)",
"ph":"X",
"pid":50448,
"tid":10433558269746414945,
"ts":20799227
}
,
{
"cat":"function",
"dur":62,
"name":"void __cdecl ScrewSandbox::Sandbox::RunLoop(void)",
"ph":"X",
"pid":50448,
"tid":10433558269746414945,
"ts":20799180
}
,
{
"cat":"function",
"dur":16,
"name":"int __cdecl ScrewSandbox::Sandbox::PullEvents(void)",
"ph":"X",
"pid":50448,
"tid":10433558269746414945,
"ts":20799257
}
,
{
"cat":"function",
"dur":15,
"name":"int __cdecl ScrewSandbox::Sandbox::Update(void)",
"ph":"X",
"pid":50448,
"tid":10433558269746414945,
"ts":20799273
}
,
{
"cat":"function",
"dur":15,
"name":"int __cdecl ScrewSandbox::Sandbox::Output(void)",
"ph":"X",
"pid":50448,
"tid":10433558269746414945,
"ts":20799289
}
,
{
"cat":"function",
"dur":61,
"name":"void __cdecl ScrewSandbox::Sandbox::RunLoop(void)",
"ph":"X",
"pid":50448,
"tid":10433558269746414945,
"ts":20799243
}
,
{
"cat":"function",
"dur":15,
"name":"int __cdecl ScrewSandbox::Sandbox::PullEvents(void)",
"ph":"X",
"pid":50448,
"tid":10433558269746414945,
"ts":20799320
}
,
{
"cat":"function",
"dur":16,
"name":"int __cdecl ScrewSandbox::Sandbox::Update(void)",
"ph":"X",
"pid":50448,
"tid":10433558269746414945,
"ts":20799335
}
,
{
"cat":"function",
"dur":15,
"name":"int __cdecl ScrewSandbox::Sandbox::Output(void)",
"ph":"X",
"pid":50448,
"tid":10433558269746414945,
"ts":20799351
}
,
{
"cat":"function",
"dur":63,
"name":"void __cdecl ScrewSandbox::Sandbox::RunLoop(void)",
"ph":"X",
"pid":50448,
"tid":10433558269746414945,
"ts":20799304
}
,
{
"cat":"function",
"dur":16,
"name":"int __cdecl ScrewSandbox::Sandbox::PullEvents(void)",
"ph":"X",
"pid":50448,
"tid":10433558269746414945,
"ts":20799383
}
,
{
"cat":"function",
"dur":16,
"name":"int __cdecl ScrewSandbox::Sandbox::Update(void)",
"ph":"X",
"pid":50448,
"tid":10433558269746414945,
"ts":20799399
}
,
{
"cat":"function",
"dur":15,
"name":"int __cdecl ScrewSandbox::Sandbox::Output(void)",
"ph":"X",
"pid":50448,
"tid":10433558269746414945,
"ts":20799415
}
,
{
"cat":"function",
"dur":63,
"name":"void __cdecl ScrewSandbox::Sandbox::RunLoop(void)",
"ph":"X",
"pid":50448,
"tid":10433558269746414945,
"ts":20799367
}
,
{
"cat":"function",
"dur":16,
"name":"int __cdecl ScrewSandbox::Sandbox::PullEvents(void)",
"ph":"X",
"pid":50448,
"tid":10433558269746414945,
"ts":20799446
}
,
{
"cat":"function",
"dur":15,
"name":"int __cdecl ScrewSandbox::Sandbox::Update(void)",
"ph":"X",
"pid":50448,
"tid":10433558269746414945,
"ts":20799462
}
,
{
"cat":"function",
"dur":16,
"name":"int __cdecl ScrewSandbox::Sandbox::Output(void)",
"ph":"X",
"pid":50448,
"tid":10433558269746414945,
"ts":20799477
}
,
{
"cat":"function",
"dur":63,
"name":"void __cdecl ScrewSandbox::Sandbox::RunLoop(void)",
"ph":"X",
"pid":50448,
"tid":10433558269746414945,
"ts":20799430
}
,
{
"cat":"function",
"dur":14,
"name":"int __cdecl ScrewSandbox::Sandbox::PullEvents(void)",
"ph":"X",
"pid":50448,
"tid":10433558269746414945,
"ts":20799509
}
,
{
"cat":"function",
"dur":15,
"name":"int __cdecl ScrewSandbox::Sandbox::Update(void)",
"ph":"X",
"pid":50448,
"tid":10433558269746414945,
"ts":20799524
}
,
{
"cat":"function",
"dur":16,
"name":"int __cdecl ScrewSandbox::Sandbox::Output(void)",
"ph":"X",
"pid":50448,
"tid":10433558269746414945,
"ts":20799539
}
,
{
"cat":"function",
"dur":62,
"name":"void __cdecl ScrewSandbox::Sandbox::RunLoop(void)",
"ph":"X",
"pid":50448,
"tid":10433558269746414945,
"ts":20799493
}
,
{
"cat":"function",
"dur":15,
"name":"int __cdecl ScrewSandbox::Sandbox::PullEvents(void)",
"ph":"X",
"pid":50448,
"tid":10433558269746414945,
"ts":20799570
}
,
{
"cat":"function",
"dur":16,
"name":"int __cdecl ScrewSandbox::Sandbox::Update(void)",
"ph":"X",
"pid":50448,
"tid":10433558269746414945,
"ts":20799585
}
,
{
"cat":"function",
"dur":16,
"name":"int __cdecl ScrewSandbox::Sandbox::Output(void)",
"ph":"X",
"pid":50448,
"tid":10433558269746414945,
"ts":20799601
}
,
{
"cat":"function",
"dur":62,
"name":"void __cdecl ScrewSandbox::Sandbox::RunLoop(void)",
"ph":"X",
"pid":50448,
"tid":10433558269746414945,
"ts":20799555
}
,
{
"cat":"function",
"dur":16,
"name":"int __cdecl ScrewSandbox::Sandbox::PullEvents(void)",
"ph":"X",
"pid":50448,
"tid":10433558269746414945,
"ts":20799632
}
,
{
"cat":"function",
"dur":15,
"name":"int __cdecl ScrewSandbox::Sandbox::Update(void)",
"ph":"X",
"pid":50448,
"tid":10433558269746414945,
"ts":20799648
}
,
{
"cat":"function",
"dur":16,
"name":"int __cdecl ScrewSandbox::Sandbox::Output(void)",
"ph":"X",
"pid":50448,
"tid":10433558269746414945,
"ts":20799663
}
,
{
"cat":"function",
"dur":62,
"name":"void __cdecl ScrewSandbox::Sandbox::RunLoop(void)",
"ph":"X",
"pid":50448,
"tid":10433558269746414945,
"ts":20799617
}
,
{
"cat":"function",
"dur":14,
"name":"int __cdecl ScrewSandbox::Sandbox::PullEvents(void)",
"ph":"X",
"pid":50448,
"tid":10433558269746414945,
"ts":20799695
}
,
{
"cat":"function",
"dur":15,
"name":"int __cdecl ScrewSandbox::Sandbox::Update(void)",
"ph":"X",
"pid":50448,
"tid":10433558269746414945,
"ts":20799710
}
,
{
"cat":"function",
"dur":16,
"name":"int __cdecl ScrewSandbox::Sandbox::Output(void)",
"ph":"X",
"pid":50448,
"tid":10433558269746414945,
"ts":20799725
}
,
{
"cat":"function",
"dur":62,
"name":"void __cdecl ScrewSandbox::Sandbox::RunLoop(void)",
"ph":"X",
"pid":50448,
"tid":10433558269746414945,
"ts":20799679
}
,
{
"cat":"function",
"dur":15,
"name":"int __cdecl ScrewSandbox::Sandbox::PullEvents(void)",
"ph":"X",
"pid":50448,
"tid":10433558269746414945,
"ts":20799756
}
,
{
"cat":"function",
"dur":16,
"name":"int __cdecl ScrewSandbox::Sandbox::Update(void)",
"ph":"X",
"pid":50448,
"tid":10433558269746414945,
"ts":20799771
}
,
{
"cat":"function",
"dur":16,
"name":"int __cdecl ScrewSandbox::Sandbox::Output(void)",
"ph":"X",
"pid":50448,
"tid":10433558269746414945,
"ts":20799787
}
,
{
"cat":"function",
"dur":62,
"name":"void __cdecl ScrewSandbox::Sandbox::RunLoop(void)",
"ph":"X",
"pid":50448,
"tid":10433558269746414945,
"ts":20799741
}
]}
